minio_act/__init__.py
minio_act/bucket.py
minio_act/client.py
minio_act/log.py
minio_act-0.0.3.dist-info/METADATA
minio_act-0.0.3.dist-info/WHEEL
minio_act-0.0.3.dist-info/top_level.txt
minio_act-0.0.3.dist-info/RECORD
