Metadata-Version: 2.1
Name: minio-act
Version: 0.0.3
Summary: Python package for interact with Minio resource
Home-page: https://github.com/trancongtuanmanh/minio-act
Author: John Doe
Author-email: manhtct.dev@gmail.com
Keywords: pypi,python
Classifier: Development Status :: 1 - Planning
Classifier: Intended Audience :: Developers
Classifier: Programming Language :: Python :: 3
Classifier: Operating System :: Unix
Classifier: Operating System :: MacOS :: MacOS X
Classifier: Operating System :: Microsoft :: Windows
Requires-Python: >=3.7
Requires-Dist: minio >=7.1.15
